odoo9_addon_project_task_dependency-9.0.1.0.0-py2.7-nspkg.pth
odoo_addons/project_task_dependency/__openerp__.py
odoo_addons/project_task_dependency/__init__.py
odoo_addons/project_task_dependency/README.rst
odoo_addons/project_task_dependency/models/project_task.py
odoo_addons/project_task_dependency/models/__init__.py
odoo_addons/project_task_dependency/i18n/ja.po
odoo_addons/project_task_dependency/i18n/lv.po
odoo_addons/project_task_dependency/i18n/zh_CN.po
odoo_addons/project_task_dependency/i18n/el.po
odoo_addons/project_task_dependency/i18n/pt.po
odoo_addons/project_task_dependency/i18n/it.po
odoo_addons/project_task_dependency/i18n/es.po
odoo_addons/project_task_dependency/i18n/ar.po
odoo_addons/project_task_dependency/i18n/lt.po
odoo_addons/project_task_dependency/i18n/ro.po
odoo_addons/project_task_dependency/i18n/tr.po
odoo_addons/project_task_dependency/i18n/mk.po
odoo_addons/project_task_dependency/i18n/hr.po
odoo_addons/project_task_dependency/i18n/hu.po
odoo_addons/project_task_dependency/i18n/gl.po
odoo_addons/project_task_dependency/i18n/ca.po
odoo_addons/project_task_dependency/i18n/es_CR.po
odoo_addons/project_task_dependency/i18n/sl.po
odoo_addons/project_task_dependency/i18n/pt_PT.po
odoo_addons/project_task_dependency/i18n/mn.po
odoo_addons/project_task_dependency/i18n/nl.po
odoo_addons/project_task_dependency/i18n/de.po
odoo_addons/project_task_dependency/i18n/fr.po
odoo_addons/project_task_dependency/i18n/pl.po
odoo_addons/project_task_dependency/i18n/pt_BR.po
odoo_addons/project_task_dependency/i18n/es_VE.po
odoo_addons/project_task_dependency/i18n/es_MX.po
odoo_addons/project_task_dependency/i18n/sv.po
odoo_addons/project_task_dependency/i18n/fi.po
odoo_addons/project_task_dependency/i18n/hr_HR.po
odoo_addons/project_task_dependency/views/project_task_view.xml
odoo_addons/project_task_dependency/tests/test_project_task_dependency.py
odoo_addons/project_task_dependency/tests/__init__.py
odoo9_addon_project_task_dependency-9.0.1.0.0.dist-info/top_level.txt
odoo9_addon_project_task_dependency-9.0.1.0.0.dist-info/WHEEL
odoo9_addon_project_task_dependency-9.0.1.0.0.dist-info/RECORD
odoo9_addon_project_task_dependency-9.0.1.0.0.dist-info/metadata.json
odoo9_addon_project_task_dependency-9.0.1.0.0.dist-info/DESCRIPTION.rst
odoo9_addon_project_task_dependency-9.0.1.0.0.dist-info/METADATA
odoo9_addon_project_task_dependency-9.0.1.0.0.dist-info/namespace_packages.txt
